LICENSE
MANIFEST.in
README.md
setup.cfg
setup.py
file_thumbnailer/ConverterManager.py
file_thumbnailer/Tools.py
file_thumbnailer/__init__.py
file_thumbnailer/exceptions.py
file_thumbnailer/py.typed
file_thumbnailer.egg-info/PKG-INFO
file_thumbnailer.egg-info/SOURCES.txt
file_thumbnailer.egg-info/dependency_links.txt
file_thumbnailer.egg-info/requires.txt
file_thumbnailer.egg-info/top_level.txt
file_thumbnailer/converters/Converter.py
file_thumbnailer/converters/ImgConverter.py
file_thumbnailer/converters/PdfConverter.py
file_thumbnailer/converters/__init__.py
file_thumbnailer/models/Dimensions.py
file_thumbnailer/models/__init__.py
tests/__init__.py
tests/conftest.py
tests/test_init.py
tests/files/sample.bmp
tests/files/sample.epub
tests/files/sample.pdf
tests/files/sample.png